htmx_view/__init__.py
htmx_view/mixins.py
htmx_view/utils.py
django_htmx_view-0.1.1.dist-info/LICENSE
django_htmx_view-0.1.1.dist-info/METADATA
django_htmx_view-0.1.1.dist-info/WHEEL
django_htmx_view-0.1.1.dist-info/RECORD
